sUTL/__init__.py
sUTL/sUTL.py
sUTL-1.0.6.dist-info/DESCRIPTION.rst
sUTL-1.0.6.dist-info/METADATA
sUTL-1.0.6.dist-info/RECORD
sUTL-1.0.6.dist-info/WHEEL
sUTL-1.0.6.dist-info/metadata.json
sUTL-1.0.6.dist-info/top_level.txt
