Metadata-Version: 2.0
Name: sUTL
Version: 1.0.6
Summary: A sUTL implementation for python
Home-page: http://www.sutllang.com/
Author: Emlyn O'Regan
Author-email: emlynoregan@gmail.com
License: MIT
Keywords: DSL Language JSON
Platform: UNKNOWN
Classifier: Development Status :: 4 - Beta
Classifier: Intended Audience :: Developers
Classifier: Topic :: Software Development :: Interpreters
Classifier: License :: OSI Approved :: MIT License
Classifier: Programming Language :: Python :: 2
Classifier: Programming Language :: Python :: 2.6
Classifier: Programming Language :: Python :: 2.7
Classifier: Programming Language :: Python :: 3
Classifier: Programming Language :: Python :: 3.3
Classifier: Programming Language :: Python :: 3.4
Classifier: Programming Language :: Python :: 3.5
